cryzen/__init__.py
cryzen/astracrypt.py
cryzen/flux.py
cryzen/nova.py
cryzen/omega.py
cryzen/terra.py
cryzen/utils.py
cryzen/zencode.py
cryzen-0.1.5.dist-info/licenses/LICENSE
cryzen-0.1.5.dist-info/METADATA
cryzen-0.1.5.dist-info/WHEEL
cryzen-0.1.5.dist-info/top_level.txt
cryzen-0.1.5.dist-info/RECORD
