Metadata-Version: 2.4
Name: cryzen
Version: 0.1.5
Summary: A powerful & modular toolkit for modern cryptography and hashing.
Home-page: https://github.com/mahadi99900/cryzen
Author: Mahadi bin Iqbal
Author-email: islammdmahadi943@gmail.com
Project-URL: Bug Tracker, https://github.com/mahadi99900/cryzen/issues
Classifier: Programming Language :: Python :: 3
Classifier: License :: OSI Approved :: MIT License
Classifier: Operating System :: OS Independent
Classifier: Topic :: Security :: Cryptography
Requires-Python: >=3.7
License-File: LICENSE
Requires-Dist: pycryptodome>=3.10.1
Dynamic: author
Dynamic: author-email
Dynamic: classifier
Dynamic: description
Dynamic: description-content-type
Dynamic: home-page
Dynamic: license-file
Dynamic: project-url
Dynamic: requires-dist
Dynamic: requires-python
Dynamic: summary
